edwh_robin_plugin/__about__.py
edwh_robin_plugin/__init__.py
edwh_robin_plugin/robin_plugin.py
edwh_robin_plugin-0.2.2.dist-info/METADATA
edwh_robin_plugin-0.2.2.dist-info/WHEEL
edwh_robin_plugin-0.2.2.dist-info/entry_points.txt
edwh_robin_plugin-0.2.2.dist-info/licenses/LICENSE.txt
edwh_robin_plugin-0.2.2.dist-info/RECORD
