Metadata-Version: 2.4
Name: edwh-robin-plugin
Version: 0.2.2
Summary: robin project with a plugin to be discovered from the edwh package
Project-URL: Documentation, https://github.com/robinvandernoord/edwh-robin-plugin#readme
Project-URL: Issues, https://github.com/robinvandernoord/edwh-robin-plugin/issues
Project-URL: Source, https://github.com/robinvandernoord/edwh-robin-plugin
Author-email: Remco Boerma <remco.b@educationwarehouse.nl>, Robin van der Noord <robin.vdn@educationwarehouse.nl>
License-Expression: MIT
License-File: LICENSE.txt
Keywords: edwh
Classifier: Development Status :: 4 - Beta
Classifier: Programming Language :: Python
Classifier: Programming Language :: Python :: 3.11
Classifier: Programming Language :: Python :: 3.12
Classifier: Programming Language :: Python :: 3.13
Classifier: Programming Language :: Python :: 3.14
Classifier: Programming Language :: Python :: Implementation :: CPython
Classifier: Programming Language :: Python :: Implementation :: PyPy
Requires-Python: >=3.11
Requires-Dist: edwh
Requires-Dist: edwh-b2-plugin
Requires-Dist: edwh-bundler-plugin
Requires-Dist: edwh-devdb-plugin
Requires-Dist: edwh-files-plugin
Requires-Dist: edwh-git-plugin
Requires-Dist: edwh-multipass-plugin
Requires-Dist: edwh-pipcompile-plugin
Requires-Dist: edwh-restic-plugin
Requires-Dist: edwh-server-provisioning-plugin
Requires-Dist: edwh-uptime-plugin
Provides-Extra: dev
Requires-Dist: hatch; extra == 'dev'
Requires-Dist: python-semantic-release<8; extra == 'dev'
